suitcase/__init__.py
suitcase/crc.py
suitcase/exceptions.py
suitcase/fields.py
suitcase/protocol.py
suitcase/structure.py
suitcase/examples/__init__.py
suitcase/examples/client_server.py
suitcase/examples/dns.py
suitcase/test/__init__.py
suitcase/test/test_crc.py
suitcase/test/test_fields.py
suitcase/test/test_protocol.py
suitcase/test/examples/__init__.py
suitcase/test/examples/test_network_stack.py
suitcase-0.11.0.dist-info/LICENSE.txt
suitcase-0.11.0.dist-info/METADATA
suitcase-0.11.0.dist-info/WHEEL
suitcase-0.11.0.dist-info/top_level.txt
suitcase-0.11.0.dist-info/RECORD
