Metadata-Version: 2.1
Name: suitcase
Version: 0.11.0
Summary: A library for specifying/parsing/packing binary protocols
Home-page: https://github.com/digidotcom/python-suitcase
Author: Paul Osborne
Author-email: paul.osborne@digi.com
License: UNKNOWN
Keywords: suitcase,construct,declarative,dsl,protocol,binary,parser,builder,pack,unpack
Platform: UNKNOWN
Classifier: Development Status :: 3 - Alpha
Classifier: Intended Audience :: Developers
Classifier: License :: OSI Approved :: Mozilla Public License 2.0 (MPL 2.0)
Classifier: Programming Language :: Python :: 2.7
Classifier: Programming Language :: Python :: 3
Classifier: Programming Language :: Python :: 3.5
Classifier: Programming Language :: Python :: 3.6
Classifier: Programming Language :: Python :: 3.7
Classifier: Topic :: Software Development :: Libraries
Requires-Dist: six
